[
    {
        "model": "csas.pubpublication",
        "pk": 7635,
        "fields": {
            "series": 3,
            "lead_region": [4],
            "title_en": "Evaluating impacts of a flexible quota system on walrus harvesting",
            "title_fr": "Évaluation des impacts d’un système de quota flexible sur la récolte de morse",
            "pub_year": 2016,
            "lead_author_2": "Hammill, M.O., Young, R.A., and Mosnier, A.",
            "pub_num": "112",
            "pages": 21,
            "pdf_size": 776,
            "description": ""
        }
    }
]
