[
    {
        "model": "csas.pubpublication",
        "pk": 3,
        "fields": {
            "series": 3,
            "lead_region": [2],
            "title_en": "Ajustment for diurnal variation in the catchability of witch flounder (Glyptocaphalus cynoglossus L.) to bottom-trawl surveys in the Gulf of St. Lawrence",
            "pub_year": 1998,
            "lead_author_2": "D. Swain, G. Poirier",
            "pub_num": "002",
            "pages": 18,
            "description": ""
        }
    }
]
