[
    {
        "model": "csas.pubpublication",
        "pk": 3732,
        "fields": {
            "series": 3,
            "lead_region": [8],
            "title_en": "Review of data quality and sampling protocols of the Shorekeepers' guide",
            "title_fr": "Examen de la qualité des données et des protocoles d'échantillonnage du Guide des gardiens du littoral",
            "pub_year": 2002,
            "lead_author_2": "G.S. Jamieson, R. Scrosati, C. Schwarz, C. Levings, and B. Smiley",
            "pub_num": "121",
            "pages": 43,
            "pdf_size": 385,
            "description": ""
        }
    }
]
