[
    {
        "model": "csas.pubpublication",
        "pk": 5228,
        "fields": {
            "series": 5,
            "lead_region": [4],
            "title_en": "Stock assessment of Northern Quebec (Nunavik) Beluga (Delphinapterus leucas)",
            "title_fr": "Évaluation du stock de bélugas du Nord du Québec (Nunavik) (Delphinapterus leucas)",
            "pub_year": 2009,
            "lead_author_2": "M.O. Hammil,  V. Lesage, J.-F Gosselin",
            "pub_num": "016",
            "pages": 12,
            "pdf_size": 115,
            "description": ""
        }
    }
]
