[
    {
        "model": "csas.pubpublication",
        "pk": 5520,
        "fields": {
            "series": 3,
            "lead_region": [6, 2],
            "title_en": "Associations of Demersal Fish with Sponge Grounds in the Northwest Atlantic Fisheries Organization Regulatory Area and Adjacent Canadian Waters",
            "title_fr": "Associations de poissons démersaux avec les fonds marins dominés par les éponges dans la zone réglementée par le Organisation des pêches de l'Atlantique Nord-Ouest et dans les eaux canadiennes adjacentes",
            "pub_year": 2010,
            "lead_author_2": "Kenchington, E., Power, D., Koen-Alonso, M.",
            "pub_num": "039",
            "pages": 33,
            "pdf_size": 331,
            "description": ""
        }
    }
]
