[
    {
        "model": "csas.pubpublication",
        "pk": 7866,
        "fields": {
            "series": 3,
            "lead_region": [2],
            "title_en": "4X5Y Haddock 2016 Framework Assessment: Modelling and Reference Points",
            "title_fr": "Évaluation du cadre de 2016 pour l'aiglefin de la division 4X5Y : Modélisation et points de référence",
            "pub_year": 2017,
            "lead_author_2": "Wang, Y., Stone, H. H., and Finley, M.",
            "pub_num": "026",
            "pages": 74,
            "pdf_size": 6088,
            "description": ""
        }
    }
]
