[
    {
        "model": "csas.pubpublication",
        "pk": 6257,
        "fields": {
            "series": 5,
            "lead_region": [8],
            "title_en": "Integrated biological status of Fraser River Sockeye Salmon (Oncorhynchus nerka) under the Wild Salmon Policy",
            "title_fr": "État biologique intégré du saumon rouge du fleuve Fraser (Oncorhynchus Nerka) en vertu de la Politique concernant le saumon sauvage",
            "pub_year": 2012,
            "lead_author_2": "Sue Grant",
            "pub_num": "056",
            "pages": 13,
            "pdf_size": 241,
            "description": ""
        }
    }
]
