[
    {
        "model": "csas.pubpublication",
        "pk": 4055,
        "fields": {
            "series": 3,
            "lead_region": [4],
            "title_en": "Physical Oceanographic Conditions in the Gulf of St. Lawrence in 2003",
            "title_fr": "Conditions d'océanographie physique dans le golfe Saint-Laurent en 2003",
            "pub_year": 2004,
            "lead_author_2": "Gilbert, D., Galbraith, P.S., Lafleur, C., Pettigrew, B.",
            "pub_num": "061",
            "pages": 67,
            "pdf_size": 6379,
            "description": ""
        }
    }
]
