[
    {
        "model": "csas.pubpublication",
        "pk": 7684,
        "fields": {
            "series": 6,
            "lead_region": [8],
            "title_en": "Supplement to the pre-season run size forecasts for Fraser River Sockeye Salmon (Oncorhynchus nerka) in 2016",
            "title_fr": "Supplément aux prévisions d’avant-saison concernant le volume de la montaison du saumon rouge du fleuve Fraser (Oncorhynchus nerka) en 2016",
            "pub_year": 2016,
            "lead_author_2": "Sue Grant",
            "pub_num": "047",
            "pages": 61,
            "pdf_size": 5971,
            "description": ""
        }
    }
]
