[
    {
        "model": "csas.pubpublication",
        "pk": 4586,
        "fields": {
            "series": 5,
            "lead_region": [8],
            "title_en": "Pre-season run size forecasts for Fraser River sockeye and pink salmon in 2007",
            "title_fr": "Prévisions d'avant-saison de l'effectif de la montaison du saumon rouge et du saumon rose du Fraser en 2007",
            "pub_year": 2006,
            "lead_author_2": "Alan Cass, Sue Grant",
            "pub_num": "043",
            "pages": 12,
            "pdf_size": 150,
            "description": ""
        }
    }
]
