[
    {
        "model": "csas.pubpublication",
        "pk": 2990,
        "fields": {
            "series": 7,
            "lead_region": [2],
            "title_en": "Updates on Selected Scotian Shelf Groundfish Stocks in 2000",
            "title_fr": "Mise à jour de certains stocks de poisson de fond du plateau néo-écossais en 2000",
            "pub_year": 2000,
            "lead_author_2": "Kees Zwanenburg",
            "pub_num": "A3-35",
            "pages": 43,
            "pdf_size": 1,
            "description": ""
        }
    }
]
