[
    {
        "model": "csas.pubpublication",
        "pk": 2524,
        "fields": {
            "series": 3,
            "lead_region": [4],
            "title_en": "Estimation of the Gulf of St. Lawrence spawning stock biomass of mackerel (Scomber scombrus L.) for 1994",
            "title_fr": "Estimation de la biomasse reproductrice du stock de maquereau (Scomber scombrus L.) du golfe du Saint-Laurent pour 1994",
            "pub_year": 1995,
            "lead_author_2": "F. Grégoire; D. D'Amours; C. Lévesque; D. Thibeault",
            "pub_num": "118",
            "pages": 81,
            "pdf_size": 4364,
            "description": ""
        }
    }
]
