[
    {
        "model": "csas.pubpublication",
        "pk": 5529,
        "fields": {
            "series": 4,
            "lead_region": [6],
            "title_en": "Proceedings of a Workshop on the Canadian Aquatic Invasive Species Rapid Response Framework; June 9-10, 2009",
            "title_fr": "Compte rendu d'un atelier sur le Cadre canadien d'intervention rapide contre les espèces aquatiques envahissantes ; 9 et 10 juin 2009",
            "pub_year": 2012,
            "lead_author_2": "Cudmore, B.",
            "pub_num": "016",
            "pages": 77,
            "pdf_size": 423,
            "description": ""
        }
    }
]
