[
    {
        "model": "csas.pubpublication",
        "pk": 6070,
        "fields": {
            "series": 3,
            "lead_region": [5],
            "title_en": "Sentinel surveys 1995-2010: Catch per unit effort (CPUE) in NAFO Subdivision 3Ps",
            "title_fr": "Relevés sentinelles 1995-2010 : prises par unité d'effort (CPUE) dans la sous-division 3Ps de l'OPANO",
            "pub_year": 2011,
            "lead_author_2": "D. Maddock Parsons & R. Stead",
            "pub_num": "083",
            "pages": 28,
            "pdf_size": 405,
            "description": ""
        }
    }
]
