[
    {
        "model": "csas.pubpublication",
        "pk": 4181,
        "fields": {
            "series": 4,
            "lead_region": [8],
            "title_en": "Proceedings of the PSARC Pelagic Subcommittee Meeting; January 25-26, 2005",
            "title_fr": "Compte rendu de la réunion du sous-comité des poissons pélagiques du CEESP; 25-26 janvier 2005",
            "pub_year": 2005,
            "lead_author_2": "Therriault, T.",
            "pub_num": "004",
            "pages": 17,
            "pdf_size": 124,
            "description": ""
        }
    }
]
