[
    {
        "model": "csas.pubpublication",
        "pk": 6420,
        "fields": {
            "series": 5,
            "lead_region": [1],
            "title_en": "Biomass limit reference point consistent with the precautionary approach for American plaice (Hippoglossoides platessoides) from the southern Gulf of St. Lawrence (NAFO Div. 4T)",
            "title_fr": "Point de référence limite de la biomasse conforme à l'approche de précaution relative à la plie canadienne (Hippoglossoides platessoides) du sud du golfe du Saint-Laurent (division 4T de l'OPANO)",
            "pub_year": 2012,
            "lead_author_2": "Rod Morin",
            "pub_num": "018",
            "pages": 10,
            "pdf_size": 159,
            "description": ""
        }
    }
]
