[
    {
        "model": "csas.pubpublication",
        "pk": 3461,
        "fields": {
            "series": 3,
            "lead_region": [2],
            "title_en": "Assessment of the scallop stock in scallop production area 1 in the Bay of Fundy for 2001",
            "title_fr": "Évaluation du stock de pétoncle de la zone de production du pétoncle 1 (baie de Fundy) en 2001",
            "pub_year": 2002,
            "lead_author_2": "D. Roddick",
            "pub_num": "015",
            "pages": 49,
            "pdf_size": 2030,
            "description": ""
        }
    }
]
