[
    {
        "model": "csas.pubpublication",
        "pk": 6565,
        "fields": {
            "series": 6,
            "lead_region": [2],
            "title_en": "Lobster (Homarus americanus) in Lobster Fishing Area 41 (4X + 5Zc): 2016 Stock Status Update",
            "title_fr": "Homard (Homarus americanus) de la zone de pêche au homard 41 (4X + 5Zc) : mise à jour de l'état du stock de 2016",
            "pub_year": 2017,
            "lead_author_2": "Lottie Bennett",
            "pub_num": "015",
            "pages": 6,
            "pdf_size": 347,
            "description": ""
        }
    }
]
