[
    {
        "model": "csas.pubpublication",
        "pk": 3257,
        "fields": {
            "series": 3,
            "lead_region": [1],
            "title_en": "Assessment of Cod in the Southern Gulf of St. Lawrence, February 2002",
            "title_fr": "Évaluation du stock de morue du sud du Golfe du St-Laurent, février 2002",
            "pub_year": 2002,
            "lead_author_2": "G. A. Chouinard, L. Currie, G. Poirier, D.P. Swain, A. Rondeau, H. Benoît, T. Hurlbut",
            "pub_num": "020",
            "pages": 113,
            "pdf_size": 3090,
            "description": ""
        }
    }
]
