[
    {
        "model": "csas.pubpublication",
        "pk": 5990,
        "fields": {
            "series": 4,
            "lead_region": [2],
            "title_en": "Proceedings of the Assessment of 4VWX Herring Maritimes Regional Science Advisory Process; April 7-8, 2011",
            "title_fr": "Compte rendu de l'évaluation du processus de consultation scientifique régionale du hareng des divisions 4VWX de la région des Maritimes; 7 au 8 avril 2011",
            "pub_year": 2013,
            "lead_author_2": "Ross Claytor",
            "pub_num": "014",
            "pages": 14,
            "pdf_size": 281,
            "description": ""
        }
    }
]
