[
    {
        "model": "csas.pubpublication",
        "pk": 8126,
        "fields": {
            "series": 4,
            "lead_region": [2],
            "title_en": "Proceedings of the Stock Assessment of Herring in NAFO Division 4VWX, April 11-12, 2018",
            "title_fr": "Compte rendu de l’examen par les pairs régional de l’évaluation des stocks de hareng dans les divisions 4VWX de l’OPANO.",
            "pub_year": 2020,
            "lead_author_2": "Jennifer Ford",
            "pub_num": "010",
            "pages": 18,
            "pdf_size": 640,
            "description": ""
        }
    }
]
