[
    {
        "model": "csas.pubpublication",
        "pk": 8383,
        "fields": {
            "series": 4,
            "lead_region": [4],
            "title_en": "Proceedings of the Regional Peer Review of the Stock Assessment of Gulf of St. Lawrence (4RST) Atlantic Halibut; February 18 -19, 2019",
            "title_fr": "Compte rendu de l’examen régional par des pairs sur l’évaluation du stock de flétan atlantique du golfe du Saint-Laurent (4RST); du 18 au 19 février 2019",
            "pub_year": 2019,
            "lead_author_2": "Sonia Dubé",
            "pub_num": "013",
            "pages": 11,
            "pdf_size": 278,
            "description": ""
        }
    }
]
