[
    {
        "model": "csas.pubpublication",
        "pk": 6737,
        "fields": {
            "series": 6,
            "lead_region": [4],
            "title_en": "Update of indicators of the status of the northern Gulf of St. Lawrence (3Pn, 4RS) cod stock in 2012",
            "title_fr": "Mise à jour des indicateurs de l'état du stock de morue du nord du golfe du Saint-Laurent (3Pn, 4RS) en 2012",
            "pub_year": 2012,
            "lead_author_2": "Johanne Gauthier",
            "pub_num": "043",
            "pages": 7,
            "pdf_size": 170,
            "description": ""
        }
    }
]
