[
    {
        "model": "csas.pubpublication",
        "pk": 2846,
        "fields": {
            "series": 3,
            "lead_region": [5],
            "title_en": "Status of Atlantic salmon (Salmo salar L.) stock of Harry's River / Pinchgut Brook, Newfoundland, 1996.",
            "pub_year": 1997,
            "lead_author_2": "Mullins, C.C, Caines, D.,  Fitzgerald, J.L.",
            "pub_num": "092",
            "pages": 27,
            "pdf_size": 959,
            "description": ""
        }
    }
]
