[
    {
        "model": "csas.pubpublication",
        "pk": 4589,
        "fields": {
            "series": 3,
            "lead_region": [2],
            "title_en": "An Assessment of the Eastern Scotian Shelf Shrimp Stock and Fishery in 2006 and Outlook for 2007, including an estimate of bycatch and evaluation of alternative fishery independent abundance indicators",
            "title_fr": "Évaluation du stock et de la pêche en 2006 pour la crevette de l'est du plateau néo-écossais et perspectives pour 2007, y compris une estimation des prises accessoires et une évaluation des indicateurs de l'abondance de rechange indépendants de la pêche",
            "pub_year": 2006,
            "lead_author_2": "Koeller, P., Covery, M., King, M.",
            "pub_num": "090",
            "pages": 67,
            "pdf_size": 2074,
            "description": ""
        }
    }
]
