[
    {
        "model": "csas.pubpublication",
        "pk": 4300,
        "fields": {
            "series": 3,
            "lead_region": [8],
            "title_en": "Forecast for southern and central British Columbia coho salmon in 2004",
            "title_fr": "Prévisions pour le saumon coho du sud et du centre de la Colombie-Britannique pour 2004",
            "pub_year": 2004,
            "lead_author_2": "Simpson, K., M. Chamberlain, J. Fagan, R. Tanasichuk, D. Dobson.",
            "pub_num": "135",
            "pages": 79,
            "pdf_size": 917,
            "description": ""
        }
    }
]
