[
    {
        "model": "csas.pubpublication",
        "pk": 6207,
        "fields": {
            "series": 3,
            "lead_region": [5],
            "title_en": "Distribution and intensity of acoustic backscatter of key species identified in the 2008 fall bottom trawl survey in NAFO Divisions 2J3KLNO",
            "title_fr": "Distribution et intensité de la radiodiffusion acoustique d'espèces clés identifiées lors du relevé d'automne au chalut de fond de 2008 dans les divisions 2J3KLNO de l'OPANO",
            "pub_year": 2011,
            "lead_author_2": "L.G.S. Mello, G.A. Rose, F.K. Mowbray, and M. Koen-Alnso",
            "pub_num": "093",
            "pages": 25,
            "pdf_size": 5612,
            "description": ""
        }
    }
]
