[
    {
        "model": "csas.pubpublication",
        "pk": 5040,
        "fields": {
            "series": 5,
            "lead_region": [8],
            "title_en": "Recovery potential assessment for the Salish Sucker (Catostomus sp.) in Canada",
            "title_fr": "Évaluation du potentiel de rétablissement du meunier de Salish (Catostomus sp.) au Canada",
            "pub_year": 2008,
            "lead_author_2": "N. Schubert",
            "pub_num": "046",
            "pages": 14,
            "pdf_size": 264,
            "description": ""
        }
    }
]
