[
    {
        "model": "csas.pubpublication",
        "pk": 4879,
        "fields": {
            "series": 4,
            "lead_region": [8],
            "title_en": "Proceedings of the PSARC Pelagic Subcommittee meeting; September 5-6, 2007",
            "title_fr": "Compte rendu de la réunion du sous-comité du CEESP sur les poissons pélagiques; Septembre 5-6, 2007",
            "pub_year": 2007,
            "lead_author_2": "Potyrala, M.",
            "pub_num": "047",
            "pages": 32,
            "pdf_size": 140,
            "description": ""
        }
    }
]
