[
    {
        "model": "csas.pubpublication",
        "pk": 4702,
        "fields": {
            "series": 3,
            "lead_region": [6, 5],
            "title_en": "Assessing recovery potential: Long-term projections and their implications for socio-economic analysis",
            "title_fr": "Évaluation du potentiel de rétablissement : projections à long terme et répercussions sur l'analyse socio-économique",
            "pub_year": 2007,
            "lead_author_2": "Shelton, P.A., B. Best, A. Cass, C. Cyr, D. Duplisea, J. Gibson, M. Hammill, S. Khwaja, M.A. Koops, K.A. Martin, R. O’Boyle, J.C. Rice, A. Sinclair, K. Smedbol, D.P. Swain, L.A. Vélez-Espino, C.C. Wood.",
            "pub_num": "045",
            "pages": 42,
            "pdf_size": 234,
            "description": ""
        }
    }
]
